scarabee/_scarabee.pyi
scarabee/__init__.py
scarabee/_scarabee.cpython-311-darwin.so
scarabee/reseau/burnable_poison_rod.py
scarabee/reseau/_ensleeve.py
scarabee/reseau/nodal_flux.py
scarabee/reseau/reflector.py
scarabee/reseau/__init__.py
scarabee/reseau/fuel_pin.py
scarabee/reseau/guide_tube.py
scarabee/reseau/pwr_assembly.py
scarabee/reseau/critical_leakage.py
scarabee-0.1.0.dist-info/RECORD
scarabee-0.1.0.dist-info/WHEEL
scarabee-0.1.0.dist-info/METADATA
scarabee-0.1.0.dist-info/licenses/LICENSE
