Metadata-Version: 2.4
Name: scarabee
Version: 0.1.0
Summary: A lattice physics code for LWR analysis.
Keywords: lattice physics,reactor physics,neutron transport,LWR
Author-Email: Hunter Belanger <hunter.belanger@gmail.com>
License-Expression: GPL-3.0-only
License-File: LICENSE
Classifier: Development Status :: 2 - Pre-Alpha
Classifier: Topic :: Scientific/Engineering
Classifier: Topic :: Scientific/Engineering :: Physics
Classifier: Programming Language :: C++
Classifier: Programming Language :: Python :: 3 :: Only
Classifier: Programming Language :: Python :: 3.9
Classifier: Programming Language :: Python :: 3.10
Classifier: Programming Language :: Python :: 3.11
Classifier: Programming Language :: Python :: 3.12
Classifier: Programming Language :: Python :: 3.13
Classifier: Operating System :: Microsoft :: Windows
Classifier: Operating System :: POSIX
Classifier: Operating System :: Unix
Classifier: Operating System :: MacOS
Project-URL: homepage, https://scarabee.readthedocs.io/en/latest/
Project-URL: documentation, https://scarabee.readthedocs.io/en/latest/
Project-URL: source, https://github.com/scarabee-dev/scarabee
Requires-Python: >=3.9
